<?xml version="1.0" encoding="UTF-8"?>
<!DOCTYPE suite SYSTEM "http://testng.org/testng-1.0.dtd">
<suite name="Failed suite [PersonnelSuite]" guice-stage="DEVELOPMENT">
  <test thread-count="5" name="PersonnelTest(failed)">
    <classes>
      <class name="test.WorkPositionTest">
        <methods>
          <include name="getWorkPosition"/>
          <include name="addWorkPosition"/>
          <include name="setDAO"/>
          <include name="closeSession"/>
          <include name="deleteWorkPosition"/>
          <include name="updateWorkPosition"/>
          <include name="setupSession"/>
        </methods>
      </class> <!-- test.WorkPositionTest -->
    </classes>
  </test> <!-- PersonnelTest(failed) -->
</suite> <!-- Failed suite [PersonnelSuite] -->
